gsheetz/__init__.py
gsheetz/connection.py
gsheetz/_util/__init__.py
gsheetz/_util/csv.py
gsheetz/views/__init__.py
gsheetz/views/basic.py
gsheetz/views/view.py
gsheetz-0.0.2.dist-info/LICENSE
gsheetz-0.0.2.dist-info/METADATA
gsheetz-0.0.2.dist-info/WHEEL
gsheetz-0.0.2.dist-info/top_level.txt
gsheetz-0.0.2.dist-info/RECORD
