Metadata-Version: 2.1
Name: gsheetz
Version: 0.0.2
Summary: A small package for accessing the google sheets API.
Home-page: https://github.com/a1liu/gsheetz
Author: A1Liu
Author-email: albertymliu@gmail.com
License: UNKNOWN
Platform: UNKNOWN
Classifier: Programming Language :: Python :: 3
Classifier: License :: OSI Approved :: GNU General Public License (GPL)
Classifier: Operating System :: OS Independent
Requires-Dist: pandas
Requires-Dist: mr-clean
Requires-Dist: google-api-python-client
Requires-Dist: oauth2client
